<?xml version="1.0"?>
<data>
dnia: 05-04-20 godzina: 19:26:17
</data>
<zachorowania>
  <dane>
    <wojewodztwo>Województwo</wojewodztwo>
    <przypadki>Liczba</przypadki>
    <zgony>Liczba zgonów</zgony>
  </dane>
  <dane>
    <wojewodztwo>Cała Polska</wojewodztwo>
    <przypadki>4102</przypadki>
    <zgony>94</zgony>
  </dane>
  <dane>
    <wojewodztwo>dolnośląskie</wojewodztwo>
    <przypadki>468</przypadki>
    <zgony>10</zgony>
  </dane>
  <dane>
    <wojewodztwo>kujawsko-pomorskie</wojewodztwo>
    <przypadki>241</przypadki>
    <zgony>1</zgony>
  </dane>
  <dane>
    <wojewodztwo>lubelskie</wojewodztwo>
    <przypadki>174</przypadki>
    <zgony>6</zgony>
  </dane>
  <dane>
    <wojewodztwo>lubuskie</wojewodztwo>
    <przypadki>59</przypadki>
    <zgony></zgony>
  </dane>
  <dane>
    <wojewodztwo>łódzkie</wojewodztwo>
    <przypadki>326</przypadki>
    <zgony>3</zgony>
  </dane>
  <dane>
    <wojewodztwo>małopolskie</wojewodztwo>
    <przypadki>327</przypadki>
    <zgony>7</zgony>
  </dane>
  <dane>
    <wojewodztwo>mazowieckie</wojewodztwo>
    <przypadki>967</przypadki>
    <zgony>20</zgony>
  </dane>
  <dane>
    <wojewodztwo>opolskie</wojewodztwo>
    <przypadki>94</przypadki>
    <zgony>1</zgony>
  </dane>
  <dane>
    <wojewodztwo>podkarpackie</wojewodztwo>
    <przypadki>149</przypadki>
    <zgony>5</zgony>
  </dane>
  <dane>
    <wojewodztwo>podlaskie</wojewodztwo>
    <przypadki>91</przypadki>
    <zgony>1</zgony>
  </dane>
  <dane>
    <wojewodztwo>pomorskie</wojewodztwo>
    <przypadki>117</przypadki>
    <zgony></zgony>
  </dane>
  <dane>
    <wojewodztwo>śląskie</wojewodztwo>
    <przypadki>537</przypadki>
    <zgony>22</zgony>
  </dane>
  <dane>
    <wojewodztwo>świętokrzyskie</wojewodztwo>
    <przypadki>93</przypadki>
    <zgony>1</zgony>
  </dane>
  <dane>
    <wojewodztwo>warmińsko-mazurskie</wojewodztwo>
    <przypadki>80</przypadki>
    <zgony>1</zgony>
  </dane>
  <dane>
    <wojewodztwo>wielkopolskie</wojewodztwo>
    <przypadki>273</przypadki>
    <zgony>14</zgony>
  </dane>
  <dane>
    <wojewodztwo>zachodniopomorskie</wojewodztwo>
    <przypadki>106</przypadki>
    <zgony>2</zgony>
  </dane>
</zachorowania>
